test_numpy_compile_pyd/__init__.py
test_numpy_compile_pyd/test_numpy_compile_pyd_main.cp37-win32.pyd
test_numpy_compile_pyd/test_numpy_compile_pyd_multi.cp37-win32.pyd
test_numpy_compile_pyd-1.0.dist-info/METADATA
test_numpy_compile_pyd-1.0.dist-info/WHEEL
test_numpy_compile_pyd-1.0.dist-info/top_level.txt
test_numpy_compile_pyd-1.0.dist-info/RECORD
