Metadata-Version: 2.1
Name: test-numpy-compile-pyd
Version: 1.0
Summary: test_numpy_compile_pyd backpack
Home-page: UNKNOWN
Author: smilencezq
Author-email: smilencezq@163.com
License: UNKNOWN
Platform: UNKNOWN
